Workbook

Sheet Menu
A1: Agregador de Dados - Imposto de Renda
A3: Navegue pelos botões abaixo (clique no texto):
A5: 📥 Lançar rendimentos | B5: Registre cada rendimento com validação automática
A6: 📊 Ver resumo | B6: Totais por categoria e por mês, com gráfico
A7: 🔗 Links rápidos | B7: Receita Federal, e-CAC, gov.br
A8: ⚙️ Listas de apoio | B8: Categorias e meses usados nas listas suspensas
A10: Legenda
A11: Texto azul = você preenche
A12: Texto preto = fórmula (não editar)
A14: Ferramenta de apoio, não substitui o programa oficial da Receita Federal.

Sheet Rendimentos
A1: Rendimentos do ano-calendário
A2: Preencha apenas as células azuis. Linha 5 é um exemplo: sobrescreva-a. Mês é calculado sozinho. | H2: ← Voltar ao Menu
E3: TOTAL: | F3: =SUM(F5:F504) -> 5000 | G3: =SUM(G5:G504) -> 450.5
A4: Data | B4: Mês | C4: Fonte pagadora | D4: CPF/CNPJ (só números) | E4: Categoria | F4: Valor bruto (R$) | G4: IR retido (R$) | H4: Observação
A5: 45688 | B5: =IF(A5="","",INDEX(Listas!$B$2:$B$13,MONTH(A5))) -> Janeiro | C5: Empresa Exemplo Ltda | D5: 12345678000199 | E5: Tributável - Salário (PJ) | F5: 5000 | G5: 450.5 | H5: Exemplo - substitua
B6: =IF(A6="","",INDEX(Listas!$B$2:$B$13,MONTH(A6)))
B7: =IF(A7="","",INDEX(Listas!$B$2:$B$13,MONTH(A7)))
B8: =IF(A8="","",INDEX(Listas!$B$2:$B$13,MONTH(A8)))
B9: =IF(A9="","",INDEX(Listas!$B$2:$B$13,MONTH(A9)))
B10: =IF(A10="","",INDEX(Listas!$B$2:$B$13,MONTH(A10)))
B11: =IF(A11="","",INDEX(Listas!$B$2:$B$13,MONTH(A11)))
B12: =IF(A12="","",INDEX(Listas!$B$2:$B$13,MONTH(A12)))
B13: =IF(A13="","",INDEX(Listas!$B$2:$B$13,MONTH(A13)))
B14: =IF(A14="","",INDEX(Listas!$B$2:$B$13,MONTH(A14)))
B15: =IF(A15="","",INDEX(Listas!$B$2:$B$13,MONTH(A15)))
B16: =IF(A16="","",INDEX(Listas!$B$2:$B$13,MONTH(A16)))
B17: =IF(A17="","",INDEX(Listas!$B$2:$B$13,MONTH(A17)))
... B504: =IF(A504="","",INDEX(Listas!$B$2:$B$13,MONTH(A504)))

Sheet Resumo
A1: Resumo para a declaração
D2: ← Voltar ao Menu
A4: Categoria | B4: Valor bruto (R$) | C4: IR retido (R$) | D4: Nº lançamentos
A5: =Listas!A2 -> Tributável - Salário (PJ) | B5: =SUMIFS(Rendimentos!$F$5:$F$504,Rendimentos!$E$5:$E$504,A5) -> 5000 | C5: =SUMIFS(Rendimentos!$G$5:$G$504,Rendimentos!$E$5:$E$504,A5) -> 450.5 | D5: =COUNTIFS(Rendimentos!$E$5:$E$504,A5) -> 1
A6: =Listas!A3 -> Tributável - Aluguel (PF) | B6: =SUMIFS(Rendimentos!$F$5:$F$504,Rendimentos!$E$5:$E$504,A6) -> 0 | C6: =SUMIFS(Rendimentos!$G$5:$G$504,Rendimentos!$E$5:$E$504,A6) -> 0 | D6: =COUNTIFS(Rendimentos!$E$5:$E$504,A6) -> 0
A7: =Listas!A4 -> Tributável - Autônomo (PF) | B7: =SUMIFS(Rendimentos!$F$5:$F$504,Rendimentos!$E$5:$E$504,A7) -> 0 | C7: =SUMIFS(Rendimentos!$G$5:$G$504,Rendimentos!$E$5:$E$504,A7) -> 0 | D7: =COUNTIFS(Rendimentos!$E$5:$E$504,A7) -> 0
A8: =Listas!A5 -> Isento - Poupança/LCI/LCA | B8: =SUMIFS(Rendimentos!$F$5:$F$504,Rendimentos!$E$5:$E$504,A8) -> 0 | C8: =SUMIFS(Rendimentos!$G$5:$G$504,Rendimentos!$E$5:$E$504,A8) -> 0 | D8: =COUNTIFS(Rendimentos!$E$5:$E$504,A8) -> 0
A9: =Listas!A6 -> Isento - Lucros e dividendos | B9: =SUMIFS(Rendimentos!$F$5:$F$504,Rendimentos!$E$5:$E$504,A9) -> 0 | C9: =SUMIFS(Rendimentos!$G$5:$G$504,Rendimentos!$E$5:$E$504,A9) -> 0 | D9: =COUNTIFS(Rendimentos!$E$5:$E$504,A9) -> 0
A10: =Listas!A7 -> Isento - Outros | B10: =SUMIFS(Rendimentos!$F$5:$F$504,Rendimentos!$E$5:$E$504,A10) -> 0 | C10: =SUMIFS(Rendimentos!$G$5:$G$504,Rendimentos!$E$5:$E$504,A10) -> 0 | D10: =COUNTIFS(Rendimentos!$E$5:$E$504,A10) -> 0
A11: =Listas!A8 -> Exclusivo na fonte - 13º salário | B11: =SUMIFS(Rendimentos!$F$5:$F$504,Rendimentos!$E$5:$E$504,A11) -> 0 | C11: =SUMIFS(Rendimentos!$G$5:$G$504,Rendimentos!$E$5:$E$504,A11) -> 0 | D11: =COUNTIFS(Rendimentos!$E$5:$E$504,A11) -> 0
A12: =Listas!A9 -> Exclusivo na fonte - Aplicações financeiras | B12: =SUMIFS(Rendimentos!$F$5:$F$504,Rendimentos!$E$5:$E$504,A12) -> 0 | C12: =SUMIFS(Rendimentos!$G$5:$G$504,Rendimentos!$E$5:$E$504,A12) -> 0 | D12: =COUNTIFS(Rendimentos!$E$5:$E$504,A12) -> 0
A13: TOTAL | B13: =SUM(B5:B12) -> 5000 | C13: =SUM(C5:C12) -> 450.5 | D13: =SUM(D5:D12) -> 1
A14: Conferência vs. aba Rendimentos | B14: =IF(ROUND(B13-Rendimentos!F3,2)=0,"OK","DIVERGE - há lançamento sem categoria") -> OK
A17: Total por mês
A18: Mês | B18: Valor bruto (R$) | C18: IR retido (R$)
A19: =Listas!B2 -> Janeiro | B19: =SUMIFS(Rendimentos!$F$5:$F$504,Rendimentos!$B$5:$B$504,A19) -> 5000 | C19: =SUMIFS(Rendimentos!$G$5:$G$504,Rendimentos!$B$5:$B$504,A19) -> 450.5
A20: =Listas!B3 -> Fevereiro | B20: =SUMIFS(Rendimentos!$F$5:$F$504,Rendimentos!$B$5:$B$504,A20) -> 0 | C20: =SUMIFS(Rendimentos!$G$5:$G$504,Rendimentos!$B$5:$B$504,A20) -> 0
A21: =Listas!B4 -> Março | B21: =SUMIFS(Rendimentos!$F$5:$F$504,Rendimentos!$B$5:$B$504,A21) -> 0 | C21: =SUMIFS(Rendimentos!$G$5:$G$504,Rendimentos!$B$5:$B$504,A21) -> 0
A22: =Listas!B5 -> Abril | B22: =SUMIFS(Rendimentos!$F$5:$F$504,Rendimentos!$B$5:$B$504,A22) -> 0 | C22: =SUMIFS(Rendimentos!$G$5:$G$504,Rendimentos!$B$5:$B$504,A22) -> 0
A23: =Listas!B6 -> Maio | B23: =SUMIFS(Rendimentos!$F$5:$F$504,Rendimentos!$B$5:$B$504,A23) -> 0 | C23: =SUMIFS(Rendimentos!$G$5:$G$504,Rendimentos!$B$5:$B$504,A23) -> 0
A24: =Listas!B7 -> Junho | B24: =SUMIFS(Rendimentos!$F$5:$F$504,Rendimentos!$B$5:$B$504,A24) -> 0 | C24: =SUMIFS(Rendimentos!$G$5:$G$504,Rendimentos!$B$5:$B$504,A24) -> 0
A25: =Listas!B8 -> Julho | B25: =SUMIFS(Rendimentos!$F$5:$F$504,Rendimentos!$B$5:$B$504,A25) -> 0 | C25: =SUMIFS(Rendimentos!$G$5:$G$504,Rendimentos!$B$5:$B$504,A25) -> 0
A26: =Listas!B9 -> Agosto | B26: =SUMIFS(Rendimentos!$F$5:$F$504,Rendimentos!$B$5:$B$504,A26) -> 0 | C26: =SUMIFS(Rendimentos!$G$5:$G$504,Rendimentos!$B$5:$B$504,A26) -> 0
A27: =Listas!B10 -> Setembro | B27: =SUMIFS(Rendimentos!$F$5:$F$504,Rendimentos!$B$5:$B$504,A27) -> 0 | C27: =SUMIFS(Rendimentos!$G$5:$G$504,Rendimentos!$B$5:$B$504,A27) -> 0
A28: =Listas!B11 -> Outubro | B28: =SUMIFS(Rendimentos!$F$5:$F$504,Rendimentos!$B$5:$B$504,A28) -> 0 | C28: =SUMIFS(Rendimentos!$G$5:$G$504,Rendimentos!$B$5:$B$504,A28) -> 0
A29: =Listas!B12 -> Novembro | B29: =SUMIFS(Rendimentos!$F$5:$F$504,Rendimentos!$B$5:$B$504,A29) -> 0 | C29: =SUMIFS(Rendimentos!$G$5:$G$504,Rendimentos!$B$5:$B$504,A29) -> 0
A30: =Listas!B13 -> Dezembro | B30: =SUMIFS(Rendimentos!$F$5:$F$504,Rendimentos!$B$5:$B$504,A30) -> 0 | C30: =SUMIFS(Rendimentos!$G$5:$G$504,Rendimentos!$B$5:$B$504,A30) -> 0

Sheet Links
A1: Links rápidos
B2: ← Voltar ao Menu
A4: Receita Federal - Imposto de Renda | B4: https://www.gov.br/receitafederal/pt-br/assuntos/meu-imposto-de-renda
A5: Portal e-CAC | B5: https://cav.receita.fazenda.gov.br/
A6: Portal gov.br | B6: https://www.gov.br/
A7: Programa IRPF (download) | B7: https://www.gov.br/receitafederal/pt-br/centrais-de-conteudo/download/pgd/dirpf
A8: Consulta situação da declaração | B8: https://www.restituicao.receita.fazenda.gov.br/
A9: Perguntas e respostas IRPF | B9: https://www.gov.br/receitafederal/pt-br/assuntos/meu-imposto-de-renda/perguntas-frequentes
A11: Confira se os endereços continuam válidos no site oficial antes de usar.

Sheet Listas
A1: Categorias | B1: Meses | D1: Aba de apoio: alimenta as listas suspensas. Edite as categorias aqui.
A2: Tributável - Salário (PJ) | B2: Janeiro
A3: Tributável - Aluguel (PF) | B3: Fevereiro
A4: Tributável - Autônomo (PF) | B4: Março
A5: Isento - Poupança/LCI/LCA | B5: Abril
A6: Isento - Lucros e dividendos | B6: Maio
A7: Isento - Outros | B7: Junho
A8: Exclusivo na fonte - 13º salário | B8: Julho
A9: Exclusivo na fonte - Aplicações financeiras | B9: Agosto
B10: Setembro
B11: Outubro
B12: Novembro
B13: Dezembro
